carberra/__init__.py
carberra/__main__.py
carberra/cli.py
carberra-0.1.0.dist-info/METADATA
carberra-0.1.0.dist-info/WHEEL
carberra-0.1.0.dist-info/entry_points.txt
carberra-0.1.0.dist-info/top_level.txt
carberra-0.1.0.dist-info/RECORD
